{"3768":{"db_id":"e_learning","query":"SELECT count(*) FROM COURSES","question":"How many courses are there in total?","query_toks":["SELECT","count","(","*",")","FROM","COURSES"],"query_toks_no_value":["select","count","(","*",")","from","courses"],"question_toks":["How","many","courses","are","there","in","total","?"]},"3769":{"db_id":"e_learning","query":"SELECT count(*) FROM COURSES","question":"Find the total number of courses offered.","query_toks":["SELECT","count","(","*",")","FROM","COURSES"],"query_toks_no_value":["select","count","(","*",")","from","courses"],"question_toks":["Find","the","total","number","of","courses","offered","."]},"3770":{"db_id":"e_learning","query":"SELECT course_description FROM COURSES WHERE course_name  =  \"database\"","question":"What are the descriptions of the courses with name \"database\"?","query_toks":["SELECT","course_description","FROM","COURSES","WHERE","course_name","=","``","database","''"],"query_toks_no_value":["select","course_description","from","courses","where","course_name","=","value"],"question_toks":["What","are","the","descriptions","of","the","courses","with","name","``","database","''","?"]},"3771":{"db_id":"e_learning","query":"SELECT course_description FROM COURSES WHERE course_name  =  \"database\"","question":"Return the description for the courses named \"database\".","query_toks":["SELECT","course_description","FROM","COURSES","WHERE","course_name","=","``","database","''"],"query_toks_no_value":["select","course_description","from","courses","where","course_name","=","value"],"question_toks":["Return","the","description","for","the","courses","named","``","database","''","."]},"3772":{"db_id":"e_learning","query":"SELECT address_line_1 FROM Course_Authors_and_Tutors WHERE personal_name\t =  \"Cathrine\"","question":"What are the addresses of the course authors or tutors with personal name \"Cathrine\"","query_toks":["SELECT","address_line_1","FROM","Course_Authors_and_Tutors","WHERE","personal_name","=","``","Cathrine","''"],"query_toks_no_value":["select","address_line_1","from","course_authors_and_tutors","where","personal_name","=","value"],"question_toks":["What","are","the","addresses","of","the","course","authors","or","tutors","with","personal","name","``","Cathrine","''"]},"3773":{"db_id":"e_learning","query":"SELECT address_line_1 FROM Course_Authors_and_Tutors WHERE personal_name\t =  \"Cathrine\"","question":"Return the addresses of the course authors or tutors whose personal name is \"Cathrine\".","query_toks":["SELECT","address_line_1","FROM","Course_Authors_and_Tutors","WHERE","personal_name","=","``","Cathrine","''"],"query_toks_no_value":["select","address_line_1","from","course_authors_and_tutors","where","personal_name","=","value"],"question_toks":["Return","the","addresses","of","the","course","authors","or","tutors","whose","personal","name","is","``","Cathrine","''","."]},"3774":{"db_id":"e_learning","query":"SELECT address_line_1 FROM Course_Authors_and_Tutors","question":"List the addresses of all the course authors or tutors.","query_toks":["SELECT","address_line_1","FROM","Course_Authors_and_Tutors"],"query_toks_no_value":["select","address_line_1","from","course_authors_and_tutors"],"question_toks":["List","the","addresses","of","all","the","course","authors","or","tutors","."]},"3775":{"db_id":"e_learning","query":"SELECT address_line_1 FROM Course_Authors_and_Tutors","question":"What is the address of each course author or tutor?","query_toks":["SELECT","address_line_1","FROM","Course_Authors_and_Tutors"],"query_toks_no_value":["select","address_line_1","from","course_authors_and_tutors"],"question_toks":["What","is","the","address","of","each","course","author","or","tutor","?"]},"3776":{"db_id":"e_learning","query":"SELECT login_name ,  family_name FROM Course_Authors_and_Tutors","question":"List all the login names and family names of course author and tutors.","query_toks":["SELECT","login_name",",","family_name","FROM","Course_Authors_and_Tutors"],"query_toks_no_value":["select","login_name",",","family_name","from","course_authors_and_tutors"],"question_toks":["List","all","the","login","names","and","family","names","of","course","author","and","tutors","."]},"3777":{"db_id":"e_learning","query":"SELECT login_name ,  family_name FROM Course_Authors_and_Tutors","question":"What are the login names and family names of course author and tutors?","query_toks":["SELECT","login_name",",","family_name","FROM","Course_Authors_and_Tutors"],"query_toks_no_value":["select","login_name",",","family_name","from","course_authors_and_tutors"],"question_toks":["What","are","the","login","names","and","family","names","of","course","author","and","tutors","?"]},"3778":{"db_id":"e_learning","query":"SELECT date_of_enrolment ,  date_of_completion FROM Student_Course_Enrolment","question":"List all the dates of enrollment and completion of students.","query_toks":["SELECT","date_of_enrolment",",","date_of_completion","FROM","Student_Course_Enrolment"],"query_toks_no_value":["select","date_of_enrolment",",","date_of_completion","from","student_course_enrolment"],"question_toks":["List","all","the","dates","of","enrollment","and","completion","of","students","."]},"3779":{"db_id":"e_learning","query":"SELECT date_of_enrolment ,  date_of_completion FROM Student_Course_Enrolment","question":"What are all the dates of enrollment and completion in record?","query_toks":["SELECT","date_of_enrolment",",","date_of_completion","FROM","Student_Course_Enrolment"],"query_toks_no_value":["select","date_of_enrolment",",","date_of_completion","from","student_course_enrolment"],"question_toks":["What","are","all","the","dates","of","enrollment","and","completion","in","record","?"]},"3780":{"db_id":"e_learning","query":"SELECT count(DISTINCT student_id) FROM Student_Course_Enrolment","question":"How many distinct students are enrolled in courses?","query_toks":["SELECT","count","(","DISTINCT","student_id",")","FROM","Student_Course_Enrolment"],"query_toks_no_value":["select","count","(","distinct","student_id",")","from","student_course_enrolment"],"question_toks":["How","many","distinct","students","are","enrolled","in","courses","?"]},"3781":{"db_id":"e_learning","query":"SELECT count(DISTINCT student_id) FROM Student_Course_Enrolment","question":"Find the number of distinct students enrolled in courses.","query_toks":["SELECT","count","(","DISTINCT","student_id",")","FROM","Student_Course_Enrolment"],"query_toks_no_value":["select","count","(","distinct","student_id",")","from","student_course_enrolment"],"question_toks":["Find","the","number","of","distinct","students","enrolled","in","courses","."]},"3782":{"db_id":"e_learning","query":"SELECT count(course_id) FROM Student_Course_Enrolment","question":"How many distinct courses are enrolled in by students?","query_toks":["SELECT","count","(","course_id",")","FROM","Student_Course_Enrolment"],"query_toks_no_value":["select","count","(","course_id",")","from","student_course_enrolment"],"question_toks":["How","many","distinct","courses","are","enrolled","in","by","students","?"]},"3783":{"db_id":"e_learning","query":"SELECT count(course_id) FROM Student_Course_Enrolment","question":"Find the number of distinct courses that have enrolled students.","query_toks":["SELECT","count","(","course_id",")","FROM","Student_Course_Enrolment"],"query_toks_no_value":["select","count","(","course_id",")","from","student_course_enrolment"],"question_toks":["Find","the","number","of","distinct","courses","that","have","enrolled","students","."]},"3784":{"db_id":"e_learning","query":"SELECT date_test_taken FROM Student_Tests_Taken WHERE test_result  =  \"Pass\"","question":"Find the dates of the tests taken with result \"Pass\".","query_toks":["SELECT","date_test_taken","FROM","Student_Tests_Taken","WHERE","test_result","=","``","Pass","''"],"query_toks_no_value":["select","date_test_taken","from","student_tests_taken","where","test_result","=","value"],"question_toks":["Find","the","dates","of","the","tests","taken","with","result","``","Pass","''","."]},"3785":{"db_id":"e_learning","query":"SELECT date_test_taken FROM Student_Tests_Taken WHERE test_result  =  \"Pass\"","question":"Which tests have \"Pass\" results? Return the dates when the tests were taken.","query_toks":["SELECT","date_test_taken","FROM","Student_Tests_Taken","WHERE","test_result","=","``","Pass","''"],"query_toks_no_value":["select","date_test_taken","from","student_tests_taken","where","test_result","=","value"],"question_toks":["Which","tests","have","``","Pass","''","results","?","Return","the","dates","when","the","tests","were","taken","."]},"3786":{"db_id":"e_learning","query":"SELECT count(*) FROM Student_Tests_Taken WHERE test_result  =  \"Fail\"","question":"How many tests have result \"Fail\"?","query_toks":["SELECT","count","(","*",")","FROM","Student_Tests_Taken","WHERE","test_result","=","``","Fail","''"],"query_toks_no_value":["select","count","(","*",")","from","student_tests_taken","where","test_result","=","value"],"question_toks":["How","many","tests","have","result","``","Fail","''","?"]},"3787":{"db_id":"e_learning","query":"SELECT count(*) FROM Student_Tests_Taken WHERE test_result  =  \"Fail\"","question":"Count the number of tests with \"Fail\" result.","query_toks":["SELECT","count","(","*",")","FROM","Student_Tests_Taken","WHERE","test_result","=","``","Fail","''"],"query_toks_no_value":["select","count","(","*",")","from","student_tests_taken","where","test_result","=","value"],"question_toks":["Count","the","number","of","tests","with","``","Fail","''","result","."]},"3788":{"db_id":"e_learning","query":"SELECT login_name FROM Students WHERE family_name  =  \"Ward\"","question":"What are the login names of the students with family name \"Ward\"?","query_toks":["SELECT","login_name","FROM","Students","WHERE","family_name","=","``","Ward","''"],"query_toks_no_value":["select","login_name","from","students","where","family_name","=","value"],"question_toks":["What","are","the","login","names","of","the","students","with","family","name","``","Ward","''","?"]},"3789":{"db_id":"e_learning","query":"SELECT login_name FROM Students WHERE family_name  =  \"Ward\"","question":"Return the login names of the students whose family name is \"Ward\".","query_toks":["SELECT","login_name","FROM","Students","WHERE","family_name","=","``","Ward","''"],"query_toks_no_value":["select","login_name","from","students","where","family_name","=","value"],"question_toks":["Return","the","login","names","of","the","students","whose","family","name","is","``","Ward","''","."]},"3790":{"db_id":"e_learning","query":"SELECT date_of_latest_logon FROM Students WHERE family_name  =  \"Jaskolski\" OR family_name  =  \"Langosh\"","question":"What are the dates of the latest logon of the students with family name \"Jaskolski\" or \"Langosh\"?","query_toks":["SELECT","date_of_latest_logon","FROM","Students","WHERE","family_name","=","``","Jaskolski","''","OR","family_name","=","``","Langosh","''"],"query_toks_no_value":["select","date_of_latest_logon","from","students","where","family_name","=","value","or","family_name","=","value"],"question_toks":["What","are","the","dates","of","the","latest","logon","of","the","students","with","family","name","``","Jaskolski","''","or","``","Langosh","''","?"]},"3791":{"db_id":"e_learning","query":"SELECT date_of_latest_logon FROM Students WHERE family_name  =  \"Jaskolski\" OR family_name  =  \"Langosh\"","question":"Find the latest logon date of the students whose family name is \"Jaskolski\" or \"Langosh\".","query_toks":["SELECT","date_of_latest_logon","FROM","Students","WHERE","family_name","=","``","Jaskolski","''","OR","family_name","=","``","Langosh","''"],"query_toks_no_value":["select","date_of_latest_logon","from","students","where","family_name","=","value","or","family_name","=","value"],"question_toks":["Find","the","latest","logon","date","of","the","students","whose","family","name","is","``","Jaskolski","''","or","``","Langosh","''","."]},"3792":{"db_id":"e_learning","query":"SELECT COUNT(*) FROM Students WHERE personal_name LIKE \"%son%\"","question":"How many students have personal names that contain the word \"son\"?","query_toks":["SELECT","COUNT","(","*",")","FROM","Students","WHERE","personal_name","LIKE","``","%","son","%","''"],"query_toks_no_value":["select","count","(","*",")","from","students","where","personal_name","like","value"],"question_toks":["How","many","students","have","personal","names","that","contain","the","word","``","son","''","?"]},"3793":{"db_id":"e_learning","query":"SELECT COUNT(*) FROM Students WHERE personal_name LIKE \"%son%\"","question":"Find the number of students who have the word \"son\" in their personal names.","query_toks":["SELECT","COUNT","(","*",")","FROM","Students","WHERE","personal_name","LIKE","``","%","son","%","''"],"query_toks_no_value":["select","count","(","*",")","from","students","where","personal_name","like","value"],"question_toks":["Find","the","number","of","students","who","have","the","word","``","son","''","in","their","personal","names","."]},"3794":{"db_id":"e_learning","query":"SELECT subject_name FROM SUBJECTS","question":"List all the subject names.","query_toks":["SELECT","subject_name","FROM","SUBJECTS"],"query_toks_no_value":["select","subject_name","from","subjects"],"question_toks":["List","all","the","subject","names","."]},"3795":{"db_id":"e_learning","query":"SELECT subject_name FROM SUBJECTS","question":"What are the names of all the subjects.","query_toks":["SELECT","subject_name","FROM","SUBJECTS"],"query_toks_no_value":["select","subject_name","from","subjects"],"question_toks":["What","are","the","names","of","all","the","subjects","."]},"3796":{"db_id":"e_learning","query":"SELECT * FROM Course_Authors_and_Tutors ORDER BY personal_name","question":"List all the information about course authors and tutors in alphabetical order of the personal name.","query_toks":["SELECT","*","FROM","Course_Authors_and_Tutors","ORDER","BY","personal_name"],"query_toks_no_value":["select","*","from","course_authors_and_tutors","order","by","personal_name"],"question_toks":["List","all","the","information","about","course","authors","and","tutors","in","alphabetical","order","of","the","personal","name","."]},"3797":{"db_id":"e_learning","query":"SELECT * FROM Course_Authors_and_Tutors ORDER BY personal_name","question":"Sort the information about course authors and tutors in alphabetical order of the personal name.","query_toks":["SELECT","*","FROM","Course_Authors_and_Tutors","ORDER","BY","personal_name"],"query_toks_no_value":["select","*","from","course_authors_and_tutors","order","by","personal_name"],"question_toks":["Sort","the","information","about","course","authors","and","tutors","in","alphabetical","order","of","the","personal","name","."]},"3798":{"db_id":"e_learning","query":"SELECT personal_name ,  family_name FROM Students ORDER BY family_name","question":"List the personal names and family names of all the students in alphabetical order of family name.","query_toks":["SELECT","personal_name",",","family_name","FROM","Students","ORDER","BY","family_name"],"query_toks_no_value":["select","personal_name",",","family_name","from","students","order","by","family_name"],"question_toks":["List","the","personal","names","and","family","names","of","all","the","students","in","alphabetical","order","of","family","name","."]},"3799":{"db_id":"e_learning","query":"SELECT personal_name ,  family_name FROM Students ORDER BY family_name","question":"What are the personal names and family names of the students? Sort the result in alphabetical order of the family name.","query_toks":["SELECT","personal_name",",","family_name","FROM","Students","ORDER","BY","family_name"],"query_toks_no_value":["select","personal_name",",","family_name","from","students","order","by","family_name"],"question_toks":["What","are","the","personal","names","and","family","names","of","the","students","?","Sort","the","result","in","alphabetical","order","of","the","family","name","."]},"3800":{"db_id":"e_learning","query":"SELECT test_result ,  COUNT(*) FROM Student_Tests_Taken GROUP BY test_result ORDER BY COUNT(*) DESC","question":"List each test result and its count in descending order of count.","query_toks":["SELECT","test_result",",","COUNT","(","*",")","FROM","Student_Tests_Taken","GROUP","BY","test_result","ORDER","BY","COUNT","(","*",")","DESC"],"query_toks_no_value":["select","test_result",",","count","(","*",")","from","student_tests_taken","group","by","test_result","order","by","count","(","*",")","desc"],"question_toks":["List","each","test","result","and","its","count","in","descending","order","of","count","."]},"3801":{"db_id":"e_learning","query":"SELECT test_result ,  COUNT(*) FROM Student_Tests_Taken GROUP BY test_result ORDER BY COUNT(*) DESC","question":"For each distinct test result, find the number of students who got the result.","query_toks":["SELECT","test_result",",","COUNT","(","*",")","FROM","Student_Tests_Taken","GROUP","BY","test_result","ORDER","BY","COUNT","(","*",")","DESC"],"query_toks_no_value":["select","test_result",",","count","(","*",")","from","student_tests_taken","group","by","test_result","order","by","count","(","*",")","desc"],"question_toks":["For","each","distinct","test","result",",","find","the","number","of","students","who","got","the","result","."]},"3802":{"db_id":"e_learning","query":"SELECT T1.login_name FROM Course_Authors_and_Tutors AS T1 JOIN Courses AS T2 ON T1.author_id  =  T2.author_id WHERE T2.course_name  =  \"advanced database\"","question":"Find the login name of the course author that teaches the course with name \"advanced database\".","query_toks":["SELECT","T1.login_name","FROM","Course_Authors_and_Tutors","AS","T1","JOIN","Courses","AS","T2","ON","T1.author_id","=","T2.author_id","WHERE","T2.course_name","=","``","advanced","database","''"],"query_toks_no_value":["select","t1",".","login_name","from","course_authors_and_tutors","as","t1","join","courses","as","t2","on","t1",".","author_id","=","t2",".","author_id","where","t2",".","course_name","=","value"],"question_toks":["Find","the","login","name","of","the","course","author","that","teaches","the","course","with","name","``","advanced","database","''","."]},"3803":{"db_id":"e_learning","query":"SELECT T1.login_name FROM Course_Authors_and_Tutors AS T1 JOIN Courses AS T2 ON T1.author_id  =  T2.author_id WHERE T2.course_name  =  \"advanced database\"","question":"Which course author teaches the \"advanced database\" course? Give me his or her login name.","query_toks":["SELECT","T1.login_name","FROM","Course_Authors_and_Tutors","AS","T1","JOIN","Courses","AS","T2","ON","T1.author_id","=","T2.author_id","WHERE","T2.course_name","=","``","advanced","database","''"],"query_toks_no_value":["select","t1",".","login_name","from","course_authors_and_tutors","as","t1","join","courses","as","t2","on","t1",".","author_id","=","t2",".","author_id","where","t2",".","course_name","=","value"],"question_toks":["Which","course","author","teaches","the","``","advanced","database","''","course","?","Give","me","his","or","her","login","name","."]},"3804":{"db_id":"e_learning","query":"SELECT T1.address_line_1 FROM Course_Authors_and_Tutors AS T1 JOIN Courses AS T2 ON T1.author_id  =  T2.author_id WHERE T2.course_name  =  \"operating system\" OR T2.course_name  =  \"data structure\"","question":"Find the addresses of the course authors who teach the course with name \"operating system\" or \"data structure\".","query_toks":["SELECT","T1.address_line_1","FROM","Course_Authors_and_Tutors","AS","T1","JOIN","Courses","AS","T2","ON","T1.author_id","=","T2.author_id","WHERE","T2.course_name","=","``","operating","system","''","OR","T2.course_name","=","``","data","structure","''"],"query_toks_no_value":["select","t1",".","address_line_1","from","course_authors_and_tutors","as","t1","join","courses","as","t2","on","t1",".","author_id","=","t2",".","author_id","where","t2",".","course_name","=","value","or","t2",".","course_name","=","value"],"question_toks":["Find","the","addresses","of","the","course","authors","who","teach","the","course","with","name","``","operating","system","''","or","``","data","structure","''","."]},"3805":{"db_id":"e_learning","query":"SELECT T1.address_line_1 FROM Course_Authors_and_Tutors AS T1 JOIN Courses AS T2 ON T1.author_id  =  T2.author_id WHERE T2.course_name  =  \"operating system\" OR T2.course_name  =  \"data structure\"","question":"What are the addresses of the course authors who teach either \"operating system\" or \"data structure\" course.","query_toks":["SELECT","T1.address_line_1","FROM","Course_Authors_and_Tutors","AS","T1","JOIN","Courses","AS","T2","ON","T1.author_id","=","T2.author_id","WHERE","T2.course_name","=","``","operating","system","''","OR","T2.course_name","=","``","data","structure","''"],"query_toks_no_value":["select","t1",".","address_line_1","from","course_authors_and_tutors","as","t1","join","courses","as","t2","on","t1",".","author_id","=","t2",".","author_id","where","t2",".","course_name","=","value","or","t2",".","course_name","=","value"],"question_toks":["What","are","the","addresses","of","the","course","authors","who","teach","either","``","operating","system","''","or","``","data","structure","''","course","."]},"3806":{"db_id":"e_learning","query":"SELECT T1.personal_name ,  T1.family_name ,  T2.author_id FROM Course_Authors_and_Tutors AS T1 JOIN Courses AS T2 ON T1.author_id  =  T2.author_id GROUP BY T2.author_id ORDER BY COUNT(*) DESC LIMIT 1","question":"Find the personal name, family name, and author ID of the course author that teaches the most courses.","query_toks":["SELECT","T1.personal_name",",","T1.family_name",",","T2.author_id","FROM","Course_Authors_and_Tutors","AS","T1","JOIN","Courses","AS","T2","ON","T1.author_id","=","T2.author_id","GROUP","BY","T2.author_id","ORDER","BY","COUNT","(","*",")","DESC","LIMIT","1"],"query_toks_no_value":["select","t1",".","personal_name",",","t1",".","family_name",",","t2",".","author_id","from","course_authors_and_tutors","as","t1","join","courses","as","t2","on","t1",".","author_id","=","t2",".","author_id","group","by","t2",".","author_id","order","by","count","(","*",")","desc","limit","value"],"question_toks":["Find","the","personal","name",",","family","name",",","and","author","ID","of","the","course","author","that","teaches","the","most","courses","."]},"3807":{"db_id":"e_learning","query":"SELECT T1.personal_name ,  T1.family_name ,  T2.author_id FROM Course_Authors_and_Tutors AS T1 JOIN Courses AS T2 ON T1.author_id  =  T2.author_id GROUP BY T2.author_id ORDER BY COUNT(*) DESC LIMIT 1","question":"What are the personal name, family name, and author ID of the course author who teaches the most courses?","query_toks":["SELECT","T1.personal_name",",","T1.family_name",",","T2.author_id","FROM","Course_Authors_and_Tutors","AS","T1","JOIN","Courses","AS","T2","ON","T1.author_id","=","T2.author_id","GROUP","BY","T2.author_id","ORDER","BY","COUNT","(","*",")","DESC","LIMIT","1"],"query_toks_no_value":["select","t1",".","personal_name",",","t1",".","family_name",",","t2",".","author_id","from","course_authors_and_tutors","as","t1","join","courses","as","t2","on","t1",".","author_id","=","t2",".","author_id","group","by","t2",".","author_id","order","by","count","(","*",")","desc","limit","value"],"question_toks":["What","are","the","personal","name",",","family","name",",","and","author","ID","of","the","course","author","who","teaches","the","most","courses","?"]},"3808":{"db_id":"e_learning","query":"SELECT T1.address_line_1 ,  T2.author_id FROM Course_Authors_and_Tutors AS T1 JOIN Courses AS T2 ON T1.author_id  =  T2.author_id GROUP BY T2.author_id HAVING Count(*)  >=  2","question":"Find the addresses and author IDs of the course authors that teach at least two courses.","query_toks":["SELECT","T1.address_line_1",",","T2.author_id","FROM","Course_Authors_and_Tutors","AS","T1","JOIN","Courses","AS","T2","ON","T1.author_id","=","T2.author_id","GROUP","BY","T2.author_id","HAVING","Count","(","*",")",">","=","2"],"query_toks_no_value":["select","t1",".","address_line_1",",","t2",".","author_id","from","course_authors_and_tutors","as","t1","join","courses","as","t2","on","t1",".","author_id","=","t2",".","author_id","group","by","t2",".","author_id","having","count","(","*",")",">","=","value"],"question_toks":["Find","the","addresses","and","author","IDs","of","the","course","authors","that","teach","at","least","two","courses","."]},"3809":{"db_id":"e_learning","query":"SELECT T1.address_line_1 ,  T2.author_id FROM Course_Authors_and_Tutors AS T1 JOIN Courses AS T2 ON T1.author_id  =  T2.author_id GROUP BY T2.author_id HAVING Count(*)  >=  2","question":"Which course authors teach two or more courses? Give me their addresses and author IDs.","query_toks":["SELECT","T1.address_line_1",",","T2.author_id","FROM","Course_Authors_and_Tutors","AS","T1","JOIN","Courses","AS","T2","ON","T1.author_id","=","T2.author_id","GROUP","BY","T2.author_id","HAVING","Count","(","*",")",">","=","2"],"query_toks_no_value":["select","t1",".","address_line_1",",","t2",".","author_id","from","course_authors_and_tutors","as","t1","join","courses","as","t2","on","t1",".","author_id","=","t2",".","author_id","group","by","t2",".","author_id","having","count","(","*",")",">","=","value"],"question_toks":["Which","course","authors","teach","two","or","more","courses","?","Give","me","their","addresses","and","author","IDs","."]},"3810":{"db_id":"e_learning","query":"SELECT T2.course_name FROM Course_Authors_and_Tutors AS T1 JOIN Courses AS T2 ON T1.author_id  =  T2.author_id WHERE T1.personal_name  =  \"Julio\"","question":"Find the names of courses taught by the tutor who has personal name \"Julio\".","query_toks":["SELECT","T2.course_name","FROM","Course_Authors_and_Tutors","AS","T1","JOIN","Courses","AS","T2","ON","T1.author_id","=","T2.author_id","WHERE","T1.personal_name","=","``","Julio","''"],"query_toks_no_value":["select","t2",".","course_name","from","course_authors_and_tutors","as","t1","join","courses","as","t2","on","t1",".","author_id","=","t2",".","author_id","where","t1",".","personal_name","=","value"],"question_toks":["Find","the","names","of","courses","taught","by","the","tutor","who","has","personal","name","``","Julio","''","."]},"3811":{"db_id":"e_learning","query":"SELECT T2.course_name FROM Course_Authors_and_Tutors AS T1 JOIN Courses AS T2 ON T1.author_id  =  T2.author_id WHERE T1.personal_name  =  \"Julio\"","question":"What are the names of the courses taught by the tutor whose personal name is \"Julio\"?","query_toks":["SELECT","T2.course_name","FROM","Course_Authors_and_Tutors","AS","T1","JOIN","Courses","AS","T2","ON","T1.author_id","=","T2.author_id","WHERE","T1.personal_name","=","``","Julio","''"],"query_toks_no_value":["select","t2",".","course_name","from","course_authors_and_tutors","as","t1","join","courses","as","t2","on","t1",".","author_id","=","t2",".","author_id","where","t1",".","personal_name","=","value"],"question_toks":["What","are","the","names","of","the","courses","taught","by","the","tutor","whose","personal","name","is","``","Julio","''","?"]},"3812":{"db_id":"e_learning","query":"SELECT T1.course_name ,  T1.course_description FROM Courses AS T1 JOIN Subjects AS T2 ON T1.subject_id  =  T2.subject_id WHERE T2.subject_name  =  \"Computer Science\"","question":"Find the names and descriptions of courses that belong to the subject named \"Computer Science\".","query_toks":["SELECT","T1.course_name",",","T1.course_description","FROM","Courses","AS","T1","JOIN","Subjects","AS","T2","ON","T1.subject_id","=","T2.subject_id","WHERE","T2.subject_name","=","``","Computer","Science","''"],"query_toks_no_value":["select","t1",".","course_name",",","t1",".","course_description","from","courses","as","t1","join","subjects","as","t2","on","t1",".","subject_id","=","t2",".","subject_id","where","t2",".","subject_name","=","value"],"question_toks":["Find","the","names","and","descriptions","of","courses","that","belong","to","the","subject","named","``","Computer","Science","''","."]},"3813":{"db_id":"e_learning","query":"SELECT T1.course_name ,  T1.course_description FROM Courses AS T1 JOIN Subjects AS T2 ON T1.subject_id  =  T2.subject_id WHERE T2.subject_name  =  \"Computer Science\"","question":"What are the names and descriptions of the all courses under the \"Computer Science\" subject?","query_toks":["SELECT","T1.course_name",",","T1.course_description","FROM","Courses","AS","T1","JOIN","Subjects","AS","T2","ON","T1.subject_id","=","T2.subject_id","WHERE","T2.subject_name","=","``","Computer","Science","''"],"query_toks_no_value":["select","t1",".","course_name",",","t1",".","course_description","from","courses","as","t1","join","subjects","as","t2","on","t1",".","subject_id","=","t2",".","subject_id","where","t2",".","subject_name","=","value"],"question_toks":["What","are","the","names","and","descriptions","of","the","all","courses","under","the","``","Computer","Science","''","subject","?"]},"3814":{"db_id":"e_learning","query":"SELECT T1.subject_id ,  T2.subject_name ,  COUNT(*) FROM Courses AS T1 JOIN Subjects AS T2 ON T1.subject_id  =  T2.subject_id GROUP BY T1.subject_id","question":"Find the subject ID, subject name, and the corresponding number of available courses for each subject.","query_toks":["SELECT","T1.subject_id",",","T2.subject_name",",","COUNT","(","*",")","FROM","Courses","AS","T1","JOIN","Subjects","AS","T2","ON","T1.subject_id","=","T2.subject_id","GROUP","BY","T1.subject_id"],"query_toks_no_value":["select","t1",".","subject_id",",","t2",".","subject_name",",","count","(","*",")","from","courses","as","t1","join","subjects","as","t2","on","t1",".","subject_id","=","t2",".","subject_id","group","by","t1",".","subject_id"],"question_toks":["Find","the","subject","ID",",","subject","name",",","and","the","corresponding","number","of","available","courses","for","each","subject","."]},"3815":{"db_id":"e_learning","query":"SELECT T1.subject_id ,  T2.subject_name ,  COUNT(*) FROM Courses AS T1 JOIN Subjects AS T2 ON T1.subject_id  =  T2.subject_id GROUP BY T1.subject_id","question":"What are the subject ID, subject name, and the number of available courses for each subject?","query_toks":["SELECT","T1.subject_id",",","T2.subject_name",",","COUNT","(","*",")","FROM","Courses","AS","T1","JOIN","Subjects","AS","T2","ON","T1.subject_id","=","T2.subject_id","GROUP","BY","T1.subject_id"],"query_toks_no_value":["select","t1",".","subject_id",",","t2",".","subject_name",",","count","(","*",")","from","courses","as","t1","join","subjects","as","t2","on","t1",".","subject_id","=","t2",".","subject_id","group","by","t1",".","subject_id"],"question_toks":["What","are","the","subject","ID",",","subject","name",",","and","the","number","of","available","courses","for","each","subject","?"]},"3816":{"db_id":"e_learning","query":"SELECT T1.subject_id ,  T2.subject_name ,  COUNT(*) FROM Courses AS T1 JOIN Subjects AS T2 ON T1.subject_id  =  T2.subject_id GROUP BY T1.subject_id ORDER BY COUNT(*) ASC","question":"Find the subject ID, name of subject and the corresponding number of courses for each subject, and sort by the course count in ascending order.","query_toks":["SELECT","T1.subject_id",",","T2.subject_name",",","COUNT","(","*",")","FROM","Courses","AS","T1","JOIN","Subjects","AS","T2","ON","T1.subject_id","=","T2.subject_id","GROUP","BY","T1.subject_id","ORDER","BY","COUNT","(","*",")","ASC"],"query_toks_no_value":["select","t1",".","subject_id",",","t2",".","subject_name",",","count","(","*",")","from","courses","as","t1","join","subjects","as","t2","on","t1",".","subject_id","=","t2",".","subject_id","group","by","t1",".","subject_id","order","by","count","(","*",")","asc"],"question_toks":["Find","the","subject","ID",",","name","of","subject","and","the","corresponding","number","of","courses","for","each","subject",",","and","sort","by","the","course","count","in","ascending","order","."]},"3817":{"db_id":"e_learning","query":"SELECT T1.subject_id ,  T2.subject_name ,  COUNT(*) FROM Courses AS T1 JOIN Subjects AS T2 ON T1.subject_id  =  T2.subject_id GROUP BY T1.subject_id ORDER BY COUNT(*) ASC","question":"List the subject ID, name of subject and the number of courses available for each subject in ascending order of the course counts.","query_toks":["SELECT","T1.subject_id",",","T2.subject_name",",","COUNT","(","*",")","FROM","Courses","AS","T1","JOIN","Subjects","AS","T2","ON","T1.subject_id","=","T2.subject_id","GROUP","BY","T1.subject_id","ORDER","BY","COUNT","(","*",")","ASC"],"query_toks_no_value":["select","t1",".","subject_id",",","t2",".","subject_name",",","count","(","*",")","from","courses","as","t1","join","subjects","as","t2","on","t1",".","subject_id","=","t2",".","subject_id","group","by","t1",".","subject_id","order","by","count","(","*",")","asc"],"question_toks":["List","the","subject","ID",",","name","of","subject","and","the","number","of","courses","available","for","each","subject","in","ascending","order","of","the","course","counts","."]},"3818":{"db_id":"e_learning","query":"SELECT T2.date_of_enrolment FROM Courses AS T1 JOIN Student_Course_Enrolment AS T2 ON T1.course_id  =  T2.course_id WHERE T1.course_name  =  \"Spanish\"","question":"What is the date of enrollment of the course named \"Spanish\"?","query_toks":["SELECT","T2.date_of_enrolment","FROM","Courses","AS","T1","JOIN","Student_Course_Enrolment","AS","T2","ON","T1.course_id","=","T2.course_id","WHERE","T1.course_name","=","``","Spanish","''"],"query_toks_no_value":["select","t2",".","date_of_enrolment","from","courses","as","t1","join","student_course_enrolment","as","t2","on","t1",".","course_id","=","t2",".","course_id","where","t1",".","course_name","=","value"],"question_toks":["What","is","the","date","of","enrollment","of","the","course","named","``","Spanish","''","?"]},"3819":{"db_id":"e_learning","query":"SELECT T2.date_of_enrolment FROM Courses AS T1 JOIN Student_Course_Enrolment AS T2 ON T1.course_id  =  T2.course_id WHERE T1.course_name  =  \"Spanish\"","question":"Find the the date of enrollment of the \"Spanish\" course.","query_toks":["SELECT","T2.date_of_enrolment","FROM","Courses","AS","T1","JOIN","Student_Course_Enrolment","AS","T2","ON","T1.course_id","=","T2.course_id","WHERE","T1.course_name","=","``","Spanish","''"],"query_toks_no_value":["select","t2",".","date_of_enrolment","from","courses","as","t1","join","student_course_enrolment","as","t2","on","t1",".","course_id","=","t2",".","course_id","where","t1",".","course_name","=","value"],"question_toks":["Find","the","the","date","of","enrollment","of","the","``","Spanish","''","course","."]},"3820":{"db_id":"e_learning","query":"SELECT T1.course_name FROM Courses AS T1 JOIN Student_Course_Enrolment AS T2 ON T1.course_id  =  T2.course_id GROUP BY T1.course_name ORDER BY COUNT(*) DESC LIMIT 1","question":"What is the name of the course that has the most student enrollment?","query_toks":["SELECT","T1.course_name","FROM","Courses","AS","T1","JOIN","Student_Course_Enrolment","AS","T2","ON","T1.course_id","=","T2.course_id","GROUP","BY","T1.course_name","ORDER","BY","COUNT","(","*",")","DESC","LIMIT","1"],"query_toks_no_value":["select","t1",".","course_name","from","courses","as","t1","join","student_course_enrolment","as","t2","on","t1",".","course_id","=","t2",".","course_id","group","by","t1",".","course_name","order","by","count","(","*",")","desc","limit","value"],"question_toks":["What","is","the","name","of","the","course","that","has","the","most","student","enrollment","?"]},"3821":{"db_id":"e_learning","query":"SELECT T1.course_name FROM Courses AS T1 JOIN Student_Course_Enrolment AS T2 ON T1.course_id  =  T2.course_id GROUP BY T1.course_name ORDER BY COUNT(*) DESC LIMIT 1","question":"Which course is enrolled in by the most students? Give me the course name.","query_toks":["SELECT","T1.course_name","FROM","Courses","AS","T1","JOIN","Student_Course_Enrolment","AS","T2","ON","T1.course_id","=","T2.course_id","GROUP","BY","T1.course_name","ORDER","BY","COUNT","(","*",")","DESC","LIMIT","1"],"query_toks_no_value":["select","t1",".","course_name","from","courses","as","t1","join","student_course_enrolment","as","t2","on","t1",".","course_id","=","t2",".","course_id","group","by","t1",".","course_name","order","by","count","(","*",")","desc","limit","value"],"question_toks":["Which","course","is","enrolled","in","by","the","most","students","?","Give","me","the","course","name","."]},"3822":{"db_id":"e_learning","query":"SELECT T1.course_name FROM Courses AS T1 JOIN Student_Course_Enrolment AS T2 ON T1.course_id  =  T2.course_id GROUP BY T1.course_name HAVING COUNT(*)  =  1","question":"What are the names of the courses that have exactly 1 student enrollment?","query_toks":["SELECT","T1.course_name","FROM","Courses","AS","T1","JOIN","Student_Course_Enrolment","AS","T2","ON","T1.course_id","=","T2.course_id","GROUP","BY","T1.course_name","HAVING","COUNT","(","*",")","=","1"],"query_toks_no_value":["select","t1",".","course_name","from","courses","as","t1","join","student_course_enrolment","as","t2","on","t1",".","course_id","=","t2",".","course_id","group","by","t1",".","course_name","having","count","(","*",")","=","value"],"question_toks":["What","are","the","names","of","the","courses","that","have","exactly","1","student","enrollment","?"]},"3823":{"db_id":"e_learning","query":"SELECT T1.course_name FROM Courses AS T1 JOIN Student_Course_Enrolment AS T2 ON T1.course_id  =  T2.course_id GROUP BY T1.course_name HAVING COUNT(*)  =  1","question":"Find the names of the courses that have just one student enrollment.","query_toks":["SELECT","T1.course_name","FROM","Courses","AS","T1","JOIN","Student_Course_Enrolment","AS","T2","ON","T1.course_id","=","T2.course_id","GROUP","BY","T1.course_name","HAVING","COUNT","(","*",")","=","1"],"query_toks_no_value":["select","t1",".","course_name","from","courses","as","t1","join","student_course_enrolment","as","t2","on","t1",".","course_id","=","t2",".","course_id","group","by","t1",".","course_name","having","count","(","*",")","=","value"],"question_toks":["Find","the","names","of","the","courses","that","have","just","one","student","enrollment","."]},"3824":{"db_id":"e_learning","query":"SELECT T1.course_description ,  T1.course_name FROM Courses AS T1 JOIN Student_Course_Enrolment AS T2 ON T1.course_id  =  T2.course_id GROUP BY T1.course_name HAVING COUNT(*)  >  2","question":"What are the descriptions and names of the courses that have student enrollment bigger than 2?","query_toks":["SELECT","T1.course_description",",","T1.course_name","FROM","Courses","AS","T1","JOIN","Student_Course_Enrolment","AS","T2","ON","T1.course_id","=","T2.course_id","GROUP","BY","T1.course_name","HAVING","COUNT","(","*",")",">","2"],"query_toks_no_value":["select","t1",".","course_description",",","t1",".","course_name","from","courses","as","t1","join","student_course_enrolment","as","t2","on","t1",".","course_id","=","t2",".","course_id","group","by","t1",".","course_name","having","count","(","*",")",">","value"],"question_toks":["What","are","the","descriptions","and","names","of","the","courses","that","have","student","enrollment","bigger","than","2","?"]},"3825":{"db_id":"e_learning","query":"SELECT T1.course_description ,  T1.course_name FROM Courses AS T1 JOIN Student_Course_Enrolment AS T2 ON T1.course_id  =  T2.course_id GROUP BY T1.course_name HAVING COUNT(*)  >  2","question":"Return the descriptions and names of the courses that have more than two students enrolled in.","query_toks":["SELECT","T1.course_description",",","T1.course_name","FROM","Courses","AS","T1","JOIN","Student_Course_Enrolment","AS","T2","ON","T1.course_id","=","T2.course_id","GROUP","BY","T1.course_name","HAVING","COUNT","(","*",")",">","2"],"query_toks_no_value":["select","t1",".","course_description",",","t1",".","course_name","from","courses","as","t1","join","student_course_enrolment","as","t2","on","t1",".","course_id","=","t2",".","course_id","group","by","t1",".","course_name","having","count","(","*",")",">","value"],"question_toks":["Return","the","descriptions","and","names","of","the","courses","that","have","more","than","two","students","enrolled","in","."]},"3826":{"db_id":"e_learning","query":"SELECT T1.course_name ,  COUNT(*) FROM Courses AS T1 JOIN Student_Course_Enrolment AS T2 ON T1.course_id  =  T2.course_id GROUP BY T1.course_name","question":"What is the name of each course and the corresponding number of student enrollment?","query_toks":["SELECT","T1.course_name",",","COUNT","(","*",")","FROM","Courses","AS","T1","JOIN","Student_Course_Enrolment","AS","T2","ON","T1.course_id","=","T2.course_id","GROUP","BY","T1.course_name"],"query_toks_no_value":["select","t1",".","course_name",",","count","(","*",")","from","courses","as","t1","join","student_course_enrolment","as","t2","on","t1",".","course_id","=","t2",".","course_id","group","by","t1",".","course_name"],"question_toks":["What","is","the","name","of","each","course","and","the","corresponding","number","of","student","enrollment","?"]},"3827":{"db_id":"e_learning","query":"SELECT T1.course_name ,  COUNT(*) FROM Courses AS T1 JOIN Student_Course_Enrolment AS T2 ON T1.course_id  =  T2.course_id GROUP BY T1.course_name","question":"List the name and the number of enrolled student for each course.","query_toks":["SELECT","T1.course_name",",","COUNT","(","*",")","FROM","Courses","AS","T1","JOIN","Student_Course_Enrolment","AS","T2","ON","T1.course_id","=","T2.course_id","GROUP","BY","T1.course_name"],"query_toks_no_value":["select","t1",".","course_name",",","count","(","*",")","from","courses","as","t1","join","student_course_enrolment","as","t2","on","t1",".","course_id","=","t2",".","course_id","group","by","t1",".","course_name"],"question_toks":["List","the","name","and","the","number","of","enrolled","student","for","each","course","."]},"3828":{"db_id":"e_learning","query":"SELECT T1.date_of_enrolment FROM Student_Course_Enrolment AS T1 JOIN Student_Tests_Taken AS T2 ON T1.registration_id  =  T2.registration_id WHERE T2.test_result  =  \"Pass\"","question":"What are the enrollment dates of all the tests that have result \"Pass\"?","query_toks":["SELECT","T1.date_of_enrolment","FROM","Student_Course_Enrolment","AS","T1","JOIN","Student_Tests_Taken","AS","T2","ON","T1.registration_id","=","T2.registration_id","WHERE","T2.test_result","=","``","Pass","''"],"query_toks_no_value":["select","t1",".","date_of_enrolment","from","student_course_enrolment","as","t1","join","student_tests_taken","as","t2","on","t1",".","registration_id","=","t2",".","registration_id","where","t2",".","test_result","=","value"],"question_toks":["What","are","the","enrollment","dates","of","all","the","tests","that","have","result","``","Pass","''","?"]},"3829":{"db_id":"e_learning","query":"SELECT T1.date_of_enrolment FROM Student_Course_Enrolment AS T1 JOIN Student_Tests_Taken AS T2 ON T1.registration_id  =  T2.registration_id WHERE T2.test_result  =  \"Pass\"","question":"Find the enrollment date for all the tests that have \"Pass\" result.","query_toks":["SELECT","T1.date_of_enrolment","FROM","Student_Course_Enrolment","AS","T1","JOIN","Student_Tests_Taken","AS","T2","ON","T1.registration_id","=","T2.registration_id","WHERE","T2.test_result","=","``","Pass","''"],"query_toks_no_value":["select","t1",".","date_of_enrolment","from","student_course_enrolment","as","t1","join","student_tests_taken","as","t2","on","t1",".","registration_id","=","t2",".","registration_id","where","t2",".","test_result","=","value"],"question_toks":["Find","the","enrollment","date","for","all","the","tests","that","have","``","Pass","''","result","."]},"3830":{"db_id":"e_learning","query":"SELECT T1.date_of_completion FROM Student_Course_Enrolment AS T1 JOIN Student_Tests_Taken AS T2 ON T1.registration_id  =  T2.registration_id WHERE T2.test_result  =  \"Fail\"","question":"What are the completion dates of all the tests that have result \"Fail\"?","query_toks":["SELECT","T1.date_of_completion","FROM","Student_Course_Enrolment","AS","T1","JOIN","Student_Tests_Taken","AS","T2","ON","T1.registration_id","=","T2.registration_id","WHERE","T2.test_result","=","``","Fail","''"],"query_toks_no_value":["select","t1",".","date_of_completion","from","student_course_enrolment","as","t1","join","student_tests_taken","as","t2","on","t1",".","registration_id","=","t2",".","registration_id","where","t2",".","test_result","=","value"],"question_toks":["What","are","the","completion","dates","of","all","the","tests","that","have","result","``","Fail","''","?"]},"3831":{"db_id":"e_learning","query":"SELECT T1.date_of_completion FROM Student_Course_Enrolment AS T1 JOIN Student_Tests_Taken AS T2 ON T1.registration_id  =  T2.registration_id WHERE T2.test_result  =  \"Fail\"","question":"Return the completion date for all the tests that have \"Fail\" result.","query_toks":["SELECT","T1.date_of_completion","FROM","Student_Course_Enrolment","AS","T1","JOIN","Student_Tests_Taken","AS","T2","ON","T1.registration_id","=","T2.registration_id","WHERE","T2.test_result","=","``","Fail","''"],"query_toks_no_value":["select","t1",".","date_of_completion","from","student_course_enrolment","as","t1","join","student_tests_taken","as","t2","on","t1",".","registration_id","=","t2",".","registration_id","where","t2",".","test_result","=","value"],"question_toks":["Return","the","completion","date","for","all","the","tests","that","have","``","Fail","''","result","."]},"3832":{"db_id":"e_learning","query":"SELECT T1.date_of_enrolment ,  T1.date_of_completion FROM Student_Course_Enrolment AS T1 JOIN Students AS T2 ON T1.student_id  =  T2.student_id WHERE T2.personal_name  =  \"Karson\"","question":"List the dates of enrollment and completion of the student with personal name \"Karson\".","query_toks":["SELECT","T1.date_of_enrolment",",","T1.date_of_completion","FROM","Student_Course_Enrolment","AS","T1","JOIN","Students","AS","T2","ON","T1.student_id","=","T2.student_id","WHERE","T2.personal_name","=","``","Karson","''"],"query_toks_no_value":["select","t1",".","date_of_enrolment",",","t1",".","date_of_completion","from","student_course_enrolment","as","t1","join","students","as","t2","on","t1",".","student_id","=","t2",".","student_id","where","t2",".","personal_name","=","value"],"question_toks":["List","the","dates","of","enrollment","and","completion","of","the","student","with","personal","name","``","Karson","''","."]},"3833":{"db_id":"e_learning","query":"SELECT T1.date_of_enrolment ,  T1.date_of_completion FROM Student_Course_Enrolment AS T1 JOIN Students AS T2 ON T1.student_id  =  T2.student_id WHERE T2.personal_name  =  \"Karson\"","question":"On what dates did the student whose personal name is \"Karson\" enroll in and complete the courses?","query_toks":["SELECT","T1.date_of_enrolment",",","T1.date_of_completion","FROM","Student_Course_Enrolment","AS","T1","JOIN","Students","AS","T2","ON","T1.student_id","=","T2.student_id","WHERE","T2.personal_name","=","``","Karson","''"],"query_toks_no_value":["select","t1",".","date_of_enrolment",",","t1",".","date_of_completion","from","student_course_enrolment","as","t1","join","students","as","t2","on","t1",".","student_id","=","t2",".","student_id","where","t2",".","personal_name","=","value"],"question_toks":["On","what","dates","did","the","student","whose","personal","name","is","``","Karson","''","enroll","in","and","complete","the","courses","?"]},"3834":{"db_id":"e_learning","query":"SELECT T1.date_of_enrolment ,  T1.date_of_completion FROM Student_Course_Enrolment AS T1 JOIN Students AS T2 ON T1.student_id  =  T2.student_id WHERE T2.family_name  =  \"Zieme\" AND T2.personal_name  =  \"Bernie\"","question":"List the dates of enrollment and completion of the student with family name \"Zieme\" and personal name \"Bernie\".","query_toks":["SELECT","T1.date_of_enrolment",",","T1.date_of_completion","FROM","Student_Course_Enrolment","AS","T1","JOIN","Students","AS","T2","ON","T1.student_id","=","T2.student_id","WHERE","T2.family_name","=","``","Zieme","''","AND","T2.personal_name","=","``","Bernie","''"],"query_toks_no_value":["select","t1",".","date_of_enrolment",",","t1",".","date_of_completion","from","student_course_enrolment","as","t1","join","students","as","t2","on","t1",".","student_id","=","t2",".","student_id","where","t2",".","family_name","=","value","and","t2",".","personal_name","=","value"],"question_toks":["List","the","dates","of","enrollment","and","completion","of","the","student","with","family","name","``","Zieme","''","and","personal","name","``","Bernie","''","."]},"3835":{"db_id":"e_learning","query":"SELECT T1.date_of_enrolment ,  T1.date_of_completion FROM Student_Course_Enrolment AS T1 JOIN Students AS T2 ON T1.student_id  =  T2.student_id WHERE T2.family_name  =  \"Zieme\" AND T2.personal_name  =  \"Bernie\"","question":"On what dates did the student with family name \"Zieme\" and personal name \"Bernie\" enroll in and complete the courses?","query_toks":["SELECT","T1.date_of_enrolment",",","T1.date_of_completion","FROM","Student_Course_Enrolment","AS","T1","JOIN","Students","AS","T2","ON","T1.student_id","=","T2.student_id","WHERE","T2.family_name","=","``","Zieme","''","AND","T2.personal_name","=","``","Bernie","''"],"query_toks_no_value":["select","t1",".","date_of_enrolment",",","t1",".","date_of_completion","from","student_course_enrolment","as","t1","join","students","as","t2","on","t1",".","student_id","=","t2",".","student_id","where","t2",".","family_name","=","value","and","t2",".","personal_name","=","value"],"question_toks":["On","what","dates","did","the","student","with","family","name","``","Zieme","''","and","personal","name","``","Bernie","''","enroll","in","and","complete","the","courses","?"]},"3836":{"db_id":"e_learning","query":"SELECT T1.student_id ,  T2.login_name FROM Student_Course_Enrolment AS T1 JOIN Students AS T2 ON T1.student_id  =  T2.student_id GROUP BY T1.student_id ORDER BY COUNT(*) DESC LIMIT 1","question":"Find the student ID and login name of the student with the most course enrollments","query_toks":["SELECT","T1.student_id",",","T2.login_name","FROM","Student_Course_Enrolment","AS","T1","JOIN","Students","AS","T2","ON","T1.student_id","=","T2.student_id","GROUP","BY","T1.student_id","ORDER","BY","COUNT","(","*",")","DESC","LIMIT","1"],"query_toks_no_value":["select","t1",".","student_id",",","t2",".","login_name","from","student_course_enrolment","as","t1","join","students","as","t2","on","t1",".","student_id","=","t2",".","student_id","group","by","t1",".","student_id","order","by","count","(","*",")","desc","limit","value"],"question_toks":["Find","the","student","ID","and","login","name","of","the","student","with","the","most","course","enrollments"]},"3837":{"db_id":"e_learning","query":"SELECT T1.student_id ,  T2.login_name FROM Student_Course_Enrolment AS T1 JOIN Students AS T2 ON T1.student_id  =  T2.student_id GROUP BY T1.student_id ORDER BY COUNT(*) DESC LIMIT 1","question":"What are the student ID and login name of the student who are enrolled in the most courses?","query_toks":["SELECT","T1.student_id",",","T2.login_name","FROM","Student_Course_Enrolment","AS","T1","JOIN","Students","AS","T2","ON","T1.student_id","=","T2.student_id","GROUP","BY","T1.student_id","ORDER","BY","COUNT","(","*",")","DESC","LIMIT","1"],"query_toks_no_value":["select","t1",".","student_id",",","t2",".","login_name","from","student_course_enrolment","as","t1","join","students","as","t2","on","t1",".","student_id","=","t2",".","student_id","group","by","t1",".","student_id","order","by","count","(","*",")","desc","limit","value"],"question_toks":["What","are","the","student","ID","and","login","name","of","the","student","who","are","enrolled","in","the","most","courses","?"]},"3838":{"db_id":"e_learning","query":"SELECT T1.student_id ,  T2.personal_name FROM Student_Course_Enrolment AS T1 JOIN Students AS T2 ON T1.student_id  =  T2.student_id GROUP BY T1.student_id HAVING COUNT(*)  >=  2","question":"Find the student ID and personal name of the student with at least two enrollments.","query_toks":["SELECT","T1.student_id",",","T2.personal_name","FROM","Student_Course_Enrolment","AS","T1","JOIN","Students","AS","T2","ON","T1.student_id","=","T2.student_id","GROUP","BY","T1.student_id","HAVING","COUNT","(","*",")",">","=","2"],"query_toks_no_value":["select","t1",".","student_id",",","t2",".","personal_name","from","student_course_enrolment","as","t1","join","students","as","t2","on","t1",".","student_id","=","t2",".","student_id","group","by","t1",".","student_id","having","count","(","*",")",">","=","value"],"question_toks":["Find","the","student","ID","and","personal","name","of","the","student","with","at","least","two","enrollments","."]},"3839":{"db_id":"e_learning","query":"SELECT T1.student_id ,  T2.personal_name FROM Student_Course_Enrolment AS T1 JOIN Students AS T2 ON T1.student_id  =  T2.student_id GROUP BY T1.student_id HAVING COUNT(*)  >=  2","question":"Which student are enrolled in at least two courses? Give me the student ID and personal name.","query_toks":["SELECT","T1.student_id",",","T2.personal_name","FROM","Student_Course_Enrolment","AS","T1","JOIN","Students","AS","T2","ON","T1.student_id","=","T2.student_id","GROUP","BY","T1.student_id","HAVING","COUNT","(","*",")",">","=","2"],"query_toks_no_value":["select","t1",".","student_id",",","t2",".","personal_name","from","student_course_enrolment","as","t1","join","students","as","t2","on","t1",".","student_id","=","t2",".","student_id","group","by","t1",".","student_id","having","count","(","*",")",">","=","value"],"question_toks":["Which","student","are","enrolled","in","at","least","two","courses","?","Give","me","the","student","ID","and","personal","name","."]},"3840":{"db_id":"e_learning","query":"SELECT T1.student_id ,  T2.middle_name FROM Student_Course_Enrolment AS T1 JOIN Students AS T2 ON T1.student_id  =  T2.student_id GROUP BY T1.student_id HAVING COUNT(*)  <=  2","question":"Find the student ID and middle name for all the students with at most two enrollments.","query_toks":["SELECT","T1.student_id",",","T2.middle_name","FROM","Student_Course_Enrolment","AS","T1","JOIN","Students","AS","T2","ON","T1.student_id","=","T2.student_id","GROUP","BY","T1.student_id","HAVING","COUNT","(","*",")","<","=","2"],"query_toks_no_value":["select","t1",".","student_id",",","t2",".","middle_name","from","student_course_enrolment","as","t1","join","students","as","t2","on","t1",".","student_id","=","t2",".","student_id","group","by","t1",".","student_id","having","count","(","*",")","<","=","value"],"question_toks":["Find","the","student","ID","and","middle","name","for","all","the","students","with","at","most","two","enrollments","."]},"3841":{"db_id":"e_learning","query":"SELECT T1.student_id ,  T2.middle_name FROM Student_Course_Enrolment AS T1 JOIN Students AS T2 ON T1.student_id  =  T2.student_id GROUP BY T1.student_id HAVING COUNT(*)  <=  2","question":"What are the student IDs and middle names of the students enrolled in at most two courses?","query_toks":["SELECT","T1.student_id",",","T2.middle_name","FROM","Student_Course_Enrolment","AS","T1","JOIN","Students","AS","T2","ON","T1.student_id","=","T2.student_id","GROUP","BY","T1.student_id","HAVING","COUNT","(","*",")","<","=","2"],"query_toks_no_value":["select","t1",".","student_id",",","t2",".","middle_name","from","student_course_enrolment","as","t1","join","students","as","t2","on","t1",".","student_id","=","t2",".","student_id","group","by","t1",".","student_id","having","count","(","*",")","<","=","value"],"question_toks":["What","are","the","student","IDs","and","middle","names","of","the","students","enrolled","in","at","most","two","courses","?"]},"3842":{"db_id":"e_learning","query":"SELECT personal_name FROM Students EXCEPT SELECT T1.personal_name FROM Students AS T1 JOIN Student_Course_Enrolment AS T2 ON T1.student_id  =  T2.student_id","question":"Find the personal names of students not enrolled in any course.","query_toks":["SELECT","personal_name","FROM","Students","EXCEPT","SELECT","T1.personal_name","FROM","Students","AS","T1","JOIN","Student_Course_Enrolment","AS","T2","ON","T1.student_id","=","T2.student_id"],"query_toks_no_value":["select","personal_name","from","students","except","select","t1",".","personal_name","from","students","as","t1","join","student_course_enrolment","as","t2","on","t1",".","student_id","=","t2",".","student_id"],"question_toks":["Find","the","personal","names","of","students","not","enrolled","in","any","course","."]},"3843":{"db_id":"e_learning","query":"SELECT personal_name FROM Students EXCEPT SELECT T1.personal_name FROM Students AS T1 JOIN Student_Course_Enrolment AS T2 ON T1.student_id  =  T2.student_id","question":"Which students not enrolled in any course? Find their personal names.","query_toks":["SELECT","personal_name","FROM","Students","EXCEPT","SELECT","T1.personal_name","FROM","Students","AS","T1","JOIN","Student_Course_Enrolment","AS","T2","ON","T1.student_id","=","T2.student_id"],"query_toks_no_value":["select","personal_name","from","students","except","select","t1",".","personal_name","from","students","as","t1","join","student_course_enrolment","as","t2","on","t1",".","student_id","=","t2",".","student_id"],"question_toks":["Which","students","not","enrolled","in","any","course","?","Find","their","personal","names","."]},"3844":{"db_id":"e_learning","query":"SELECT count(*) FROM Students WHERE student_id NOT IN (SELECT student_id FROM Student_Course_Enrolment)","question":"How many students did not have any course enrollment?","query_toks":["SELECT","count","(","*",")","FROM","Students","WHERE","student_id","NOT","IN","(","SELECT","student_id","FROM","Student_Course_Enrolment",")"],"query_toks_no_value":["select","count","(","*",")","from","students","where","student_id","not","in","(","select","student_id","from","student_course_enrolment",")"],"question_toks":["How","many","students","did","not","have","any","course","enrollment","?"]},"3845":{"db_id":"e_learning","query":"SELECT count(*) FROM Students WHERE student_id NOT IN (SELECT student_id FROM Student_Course_Enrolment)","question":"Count the number of students who did not enroll in any course.","query_toks":["SELECT","count","(","*",")","FROM","Students","WHERE","student_id","NOT","IN","(","SELECT","student_id","FROM","Student_Course_Enrolment",")"],"query_toks_no_value":["select","count","(","*",")","from","students","where","student_id","not","in","(","select","student_id","from","student_course_enrolment",")"],"question_toks":["Count","the","number","of","students","who","did","not","enroll","in","any","course","."]},"3846":{"db_id":"e_learning","query":"SELECT login_name FROM Course_Authors_and_Tutors INTERSECT SELECT login_name FROM Students","question":"Find the common login name of course authors and students.","query_toks":["SELECT","login_name","FROM","Course_Authors_and_Tutors","INTERSECT","SELECT","login_name","FROM","Students"],"query_toks_no_value":["select","login_name","from","course_authors_and_tutors","intersect","select","login_name","from","students"],"question_toks":["Find","the","common","login","name","of","course","authors","and","students","."]},"3847":{"db_id":"e_learning","query":"SELECT login_name FROM Course_Authors_and_Tutors INTERSECT SELECT login_name FROM Students","question":"What are the login names used both by some course authors and some students?","query_toks":["SELECT","login_name","FROM","Course_Authors_and_Tutors","INTERSECT","SELECT","login_name","FROM","Students"],"query_toks_no_value":["select","login_name","from","course_authors_and_tutors","intersect","select","login_name","from","students"],"question_toks":["What","are","the","login","names","used","both","by","some","course","authors","and","some","students","?"]},"3848":{"db_id":"e_learning","query":"SELECT personal_name FROM Course_Authors_and_Tutors INTERSECT SELECT personal_name FROM Students","question":"Find the common personal name of course authors and students.","query_toks":["SELECT","personal_name","FROM","Course_Authors_and_Tutors","INTERSECT","SELECT","personal_name","FROM","Students"],"query_toks_no_value":["select","personal_name","from","course_authors_and_tutors","intersect","select","personal_name","from","students"],"question_toks":["Find","the","common","personal","name","of","course","authors","and","students","."]},"3849":{"db_id":"e_learning","query":"SELECT personal_name FROM Course_Authors_and_Tutors INTERSECT SELECT personal_name FROM Students","question":"What are the personal names used both by some course authors and some students?","query_toks":["SELECT","personal_name","FROM","Course_Authors_and_Tutors","INTERSECT","SELECT","personal_name","FROM","Students"],"query_toks_no_value":["select","personal_name","from","course_authors_and_tutors","intersect","select","personal_name","from","students"],"question_toks":["What","are","the","personal","names","used","both","by","some","course","authors","and","some","students","?"]}}