{"301":{"db_id":"product_catalog","query":"SELECT distinct(catalog_entry_name) FROM catalog_contents","question":"Find the names of all the catalog entries.","query_toks":["SELECT","distinct","(","catalog_entry_name",")","FROM","catalog_contents"],"query_toks_no_value":["select","distinct","(","catalog_entry_name",")","from","catalog_contents"],"question_toks":["Find","the","names","of","all","the","catalog","entries","."]},"302":{"db_id":"product_catalog","query":"SELECT distinct(catalog_entry_name) FROM catalog_contents","question":"What are all the catalog entry names?","query_toks":["SELECT","distinct","(","catalog_entry_name",")","FROM","catalog_contents"],"query_toks_no_value":["select","distinct","(","catalog_entry_name",")","from","catalog_contents"],"question_toks":["What","are","all","the","catalog","entry","names","?"]},"303":{"db_id":"product_catalog","query":"SELECT attribute_data_type FROM Attribute_Definitions GROUP BY attribute_data_type HAVING count(*)  >  3","question":"Find the list of attribute data types possessed by more than 3 attribute definitions.","query_toks":["SELECT","attribute_data_type","FROM","Attribute_Definitions","GROUP","BY","attribute_data_type","HAVING","count","(","*",")",">","3"],"query_toks_no_value":["select","attribute_data_type","from","attribute_definitions","group","by","attribute_data_type","having","count","(","*",")",">","value"],"question_toks":["Find","the","list","of","attribute","data","types","possessed","by","more","than","3","attribute","definitions","."]},"304":{"db_id":"product_catalog","query":"SELECT attribute_data_type FROM Attribute_Definitions GROUP BY attribute_data_type HAVING count(*)  >  3","question":"What are the attribute data types with more than 3 attribute definitions?","query_toks":["SELECT","attribute_data_type","FROM","Attribute_Definitions","GROUP","BY","attribute_data_type","HAVING","count","(","*",")",">","3"],"query_toks_no_value":["select","attribute_data_type","from","attribute_definitions","group","by","attribute_data_type","having","count","(","*",")",">","value"],"question_toks":["What","are","the","attribute","data","types","with","more","than","3","attribute","definitions","?"]},"305":{"db_id":"product_catalog","query":"SELECT attribute_data_type FROM Attribute_Definitions WHERE attribute_name  =  \"Green\"","question":"What is the attribute data type of the attribute with name \"Green\"?","query_toks":["SELECT","attribute_data_type","FROM","Attribute_Definitions","WHERE","attribute_name","=","``","Green","''"],"query_toks_no_value":["select","attribute_data_type","from","attribute_definitions","where","attribute_name","=","value"],"question_toks":["What","is","the","attribute","data","type","of","the","attribute","with","name","``","Green","''","?"]},"306":{"db_id":"product_catalog","query":"SELECT attribute_data_type FROM Attribute_Definitions WHERE attribute_name  =  \"Green\"","question":"Find the attribute data type for the attribute named \"Green\".","query_toks":["SELECT","attribute_data_type","FROM","Attribute_Definitions","WHERE","attribute_name","=","``","Green","''"],"query_toks_no_value":["select","attribute_data_type","from","attribute_definitions","where","attribute_name","=","value"],"question_toks":["Find","the","attribute","data","type","for","the","attribute","named","``","Green","''","."]},"307":{"db_id":"product_catalog","query":"SELECT catalog_level_name ,  catalog_level_number FROM Catalog_Structure WHERE catalog_level_number BETWEEN 5 AND 10","question":"Find the name and level of catalog structure with level between 5 and 10.","query_toks":["SELECT","catalog_level_name",",","catalog_level_number","FROM","Catalog_Structure","WHERE","catalog_level_number","BETWEEN","5","AND","10"],"query_toks_no_value":["select","catalog_level_name",",","catalog_level_number","from","catalog_structure","where","catalog_level_number","between","value","and","value"],"question_toks":["Find","the","name","and","level","of","catalog","structure","with","level","between","5","and","10","."]},"308":{"db_id":"product_catalog","query":"SELECT catalog_level_name ,  catalog_level_number FROM Catalog_Structure WHERE catalog_level_number BETWEEN 5 AND 10","question":"What are the name and level of catalog structure with level number between 5 and 10","query_toks":["SELECT","catalog_level_name",",","catalog_level_number","FROM","Catalog_Structure","WHERE","catalog_level_number","BETWEEN","5","AND","10"],"query_toks_no_value":["select","catalog_level_name",",","catalog_level_number","from","catalog_structure","where","catalog_level_number","between","value","and","value"],"question_toks":["What","are","the","name","and","level","of","catalog","structure","with","level","number","between","5","and","10"]},"309":{"db_id":"product_catalog","query":"SELECT distinct(catalog_publisher) FROM catalogs WHERE catalog_publisher LIKE \"%Murray%\"","question":"Find all the catalog publishers whose name contains \"Murray\"","query_toks":["SELECT","distinct","(","catalog_publisher",")","FROM","catalogs","WHERE","catalog_publisher","LIKE","``","%","Murray","%","''"],"query_toks_no_value":["select","distinct","(","catalog_publisher",")","from","catalogs","where","catalog_publisher","like","value"],"question_toks":["Find","all","the","catalog","publishers","whose","name","contains","``","Murray","''"]},"310":{"db_id":"product_catalog","query":"SELECT distinct(catalog_publisher) FROM catalogs WHERE catalog_publisher LIKE \"%Murray%\"","question":"Which catalog publishers have substring \"Murray\" in their names?","query_toks":["SELECT","distinct","(","catalog_publisher",")","FROM","catalogs","WHERE","catalog_publisher","LIKE","``","%","Murray","%","''"],"query_toks_no_value":["select","distinct","(","catalog_publisher",")","from","catalogs","where","catalog_publisher","like","value"],"question_toks":["Which","catalog","publishers","have","substring","``","Murray","''","in","their","names","?"]},"311":{"db_id":"product_catalog","query":"SELECT catalog_publisher FROM catalogs GROUP BY catalog_publisher ORDER BY count(*) DESC LIMIT 1","question":"Which catalog publisher has published the most catalogs?","query_toks":["SELECT","catalog_publisher","FROM","catalogs","GROUP","BY","catalog_publisher","ORDER","BY","count","(","*",")","DESC","LIMIT","1"],"query_toks_no_value":["select","catalog_publisher","from","catalogs","group","by","catalog_publisher","order","by","count","(","*",")","desc","limit","value"],"question_toks":["Which","catalog","publisher","has","published","the","most","catalogs","?"]},"312":{"db_id":"product_catalog","query":"SELECT catalog_publisher FROM catalogs GROUP BY catalog_publisher ORDER BY count(*) DESC LIMIT 1","question":"Find the catalog publisher that has the most catalogs.","query_toks":["SELECT","catalog_publisher","FROM","catalogs","GROUP","BY","catalog_publisher","ORDER","BY","count","(","*",")","DESC","LIMIT","1"],"query_toks_no_value":["select","catalog_publisher","from","catalogs","group","by","catalog_publisher","order","by","count","(","*",")","desc","limit","value"],"question_toks":["Find","the","catalog","publisher","that","has","the","most","catalogs","."]},"313":{"db_id":"product_catalog","query":"SELECT t1.catalog_name ,  t1.date_of_publication FROM catalogs AS t1 JOIN catalog_structure AS t2 ON t1.catalog_id  =  t2.catalog_id WHERE catalog_level_number  >  5","question":"Find the names and publication dates of all catalogs that have catalog level number greater than 5.","query_toks":["SELECT","t1.catalog_name",",","t1.date_of_publication","FROM","catalogs","AS","t1","JOIN","catalog_structure","AS","t2","ON","t1.catalog_id","=","t2.catalog_id","WHERE","catalog_level_number",">","5"],"query_toks_no_value":["select","t1",".","catalog_name",",","t1",".","date_of_publication","from","catalogs","as","t1","join","catalog_structure","as","t2","on","t1",".","catalog_id","=","t2",".","catalog_id","where","catalog_level_number",">","value"],"question_toks":["Find","the","names","and","publication","dates","of","all","catalogs","that","have","catalog","level","number","greater","than","5","."]},"314":{"db_id":"product_catalog","query":"SELECT t1.catalog_name ,  t1.date_of_publication FROM catalogs AS t1 JOIN catalog_structure AS t2 ON t1.catalog_id  =  t2.catalog_id WHERE catalog_level_number  >  5","question":"What are the name and publication date of the catalogs with catalog level number above 5?","query_toks":["SELECT","t1.catalog_name",",","t1.date_of_publication","FROM","catalogs","AS","t1","JOIN","catalog_structure","AS","t2","ON","t1.catalog_id","=","t2.catalog_id","WHERE","catalog_level_number",">","5"],"query_toks_no_value":["select","t1",".","catalog_name",",","t1",".","date_of_publication","from","catalogs","as","t1","join","catalog_structure","as","t2","on","t1",".","catalog_id","=","t2",".","catalog_id","where","catalog_level_number",">","value"],"question_toks":["What","are","the","name","and","publication","date","of","the","catalogs","with","catalog","level","number","above","5","?"]},"315":{"db_id":"product_catalog","query":"SELECT t1.catalog_entry_name FROM Catalog_Contents AS t1 JOIN Catalog_Contents_Additional_Attributes AS t2 ON t1.catalog_entry_id  =  t2.catalog_entry_id WHERE t2.attribute_value  =  (SELECT attribute_value FROM Catalog_Contents_Additional_Attributes GROUP BY attribute_value ORDER BY count(*) DESC LIMIT 1)","question":"What are the entry names of catalog with the attribute possessed by most entries.","query_toks":["SELECT","t1.catalog_entry_name","FROM","Catalog_Contents","AS","t1","JOIN","Catalog_Contents_Additional_Attributes","AS","t2","ON","t1.catalog_entry_id","=","t2.catalog_entry_id","WHERE","t2.attribute_value","=","(","SELECT","attribute_value","FROM","Catalog_Contents_Additional_Attributes","GROUP","BY","attribute_value","ORDER","BY","count","(","*",")","DESC","LIMIT","1",")"],"query_toks_no_value":["select","t1",".","catalog_entry_name","from","catalog_contents","as","t1","join","catalog_contents_additional_attributes","as","t2","on","t1",".","catalog_entry_id","=","t2",".","catalog_entry_id","where","t2",".","attribute_value","=","(","select","attribute_value","from","catalog_contents_additional_attributes","group","by","attribute_value","order","by","count","(","*",")","desc","limit","value",")"],"question_toks":["What","are","the","entry","names","of","catalog","with","the","attribute","possessed","by","most","entries","."]},"316":{"db_id":"product_catalog","query":"SELECT t1.catalog_entry_name FROM Catalog_Contents AS t1 JOIN Catalog_Contents_Additional_Attributes AS t2 ON t1.catalog_entry_id  =  t2.catalog_entry_id WHERE t2.attribute_value  =  (SELECT attribute_value FROM Catalog_Contents_Additional_Attributes GROUP BY attribute_value ORDER BY count(*) DESC LIMIT 1)","question":"Find the entry names of the catalog with the attribute that have the most entries.","query_toks":["SELECT","t1.catalog_entry_name","FROM","Catalog_Contents","AS","t1","JOIN","Catalog_Contents_Additional_Attributes","AS","t2","ON","t1.catalog_entry_id","=","t2.catalog_entry_id","WHERE","t2.attribute_value","=","(","SELECT","attribute_value","FROM","Catalog_Contents_Additional_Attributes","GROUP","BY","attribute_value","ORDER","BY","count","(","*",")","DESC","LIMIT","1",")"],"query_toks_no_value":["select","t1",".","catalog_entry_name","from","catalog_contents","as","t1","join","catalog_contents_additional_attributes","as","t2","on","t1",".","catalog_entry_id","=","t2",".","catalog_entry_id","where","t2",".","attribute_value","=","(","select","attribute_value","from","catalog_contents_additional_attributes","group","by","attribute_value","order","by","count","(","*",")","desc","limit","value",")"],"question_toks":["Find","the","entry","names","of","the","catalog","with","the","attribute","that","have","the","most","entries","."]},"317":{"db_id":"product_catalog","query":"SELECT catalog_entry_name FROM catalog_contents ORDER BY price_in_dollars DESC LIMIT 1","question":"What is the entry name of the most expensive catalog (in USD)?","query_toks":["SELECT","catalog_entry_name","FROM","catalog_contents","ORDER","BY","price_in_dollars","DESC","LIMIT","1"],"query_toks_no_value":["select","catalog_entry_name","from","catalog_contents","order","by","price_in_dollars","desc","limit","value"],"question_toks":["What","is","the","entry","name","of","the","most","expensive","catalog","(","in","USD",")","?"]},"318":{"db_id":"product_catalog","query":"SELECT catalog_entry_name FROM catalog_contents ORDER BY price_in_dollars DESC LIMIT 1","question":"Find the entry name of the catalog with the highest price (in USD).","query_toks":["SELECT","catalog_entry_name","FROM","catalog_contents","ORDER","BY","price_in_dollars","DESC","LIMIT","1"],"query_toks_no_value":["select","catalog_entry_name","from","catalog_contents","order","by","price_in_dollars","desc","limit","value"],"question_toks":["Find","the","entry","name","of","the","catalog","with","the","highest","price","(","in","USD",")","."]},"319":{"db_id":"product_catalog","query":"SELECT t2.catalog_level_name FROM catalog_contents AS t1 JOIN catalog_structure AS t2 ON t1.catalog_level_number  =  t2.catalog_level_number ORDER BY t1.price_in_dollars LIMIT 1","question":"What is the level name of the cheapest catalog (in USD)?","query_toks":["SELECT","t2.catalog_level_name","FROM","catalog_contents","AS","t1","JOIN","catalog_structure","AS","t2","ON","t1.catalog_level_number","=","t2.catalog_level_number","ORDER","BY","t1.price_in_dollars","LIMIT","1"],"query_toks_no_value":["select","t2",".","catalog_level_name","from","catalog_contents","as","t1","join","catalog_structure","as","t2","on","t1",".","catalog_level_number","=","t2",".","catalog_level_number","order","by","t1",".","price_in_dollars","limit","value"],"question_toks":["What","is","the","level","name","of","the","cheapest","catalog","(","in","USD",")","?"]},"320":{"db_id":"product_catalog","query":"SELECT t2.catalog_level_name FROM catalog_contents AS t1 JOIN catalog_structure AS t2 ON t1.catalog_level_number  =  t2.catalog_level_number ORDER BY t1.price_in_dollars LIMIT 1","question":"Find the level name of the catalog with the lowest price (in USD).","query_toks":["SELECT","t2.catalog_level_name","FROM","catalog_contents","AS","t1","JOIN","catalog_structure","AS","t2","ON","t1.catalog_level_number","=","t2.catalog_level_number","ORDER","BY","t1.price_in_dollars","LIMIT","1"],"query_toks_no_value":["select","t2",".","catalog_level_name","from","catalog_contents","as","t1","join","catalog_structure","as","t2","on","t1",".","catalog_level_number","=","t2",".","catalog_level_number","order","by","t1",".","price_in_dollars","limit","value"],"question_toks":["Find","the","level","name","of","the","catalog","with","the","lowest","price","(","in","USD",")","."]},"321":{"db_id":"product_catalog","query":"SELECT avg(price_in_euros) ,  min(price_in_euros) FROM catalog_contents","question":"What are the average and minimum price (in Euro) of all products?","query_toks":["SELECT","avg","(","price_in_euros",")",",","min","(","price_in_euros",")","FROM","catalog_contents"],"query_toks_no_value":["select","avg","(","price_in_euros",")",",","min","(","price_in_euros",")","from","catalog_contents"],"question_toks":["What","are","the","average","and","minimum","price","(","in","Euro",")","of","all","products","?"]},"322":{"db_id":"product_catalog","query":"SELECT avg(price_in_euros) ,  min(price_in_euros) FROM catalog_contents","question":"Give me the average and minimum price (in Euro) of the products.","query_toks":["SELECT","avg","(","price_in_euros",")",",","min","(","price_in_euros",")","FROM","catalog_contents"],"query_toks_no_value":["select","avg","(","price_in_euros",")",",","min","(","price_in_euros",")","from","catalog_contents"],"question_toks":["Give","me","the","average","and","minimum","price","(","in","Euro",")","of","the","products","."]},"323":{"db_id":"product_catalog","query":"SELECT catalog_entry_name FROM catalog_contents ORDER BY height DESC LIMIT 1","question":"What is the product with the highest height? Give me the catalog entry name.","query_toks":["SELECT","catalog_entry_name","FROM","catalog_contents","ORDER","BY","height","DESC","LIMIT","1"],"query_toks_no_value":["select","catalog_entry_name","from","catalog_contents","order","by","height","desc","limit","value"],"question_toks":["What","is","the","product","with","the","highest","height","?","Give","me","the","catalog","entry","name","."]},"324":{"db_id":"product_catalog","query":"SELECT catalog_entry_name FROM catalog_contents ORDER BY height DESC LIMIT 1","question":"Which catalog content has the highest height? Give me the catalog entry name.","query_toks":["SELECT","catalog_entry_name","FROM","catalog_contents","ORDER","BY","height","DESC","LIMIT","1"],"query_toks_no_value":["select","catalog_entry_name","from","catalog_contents","order","by","height","desc","limit","value"],"question_toks":["Which","catalog","content","has","the","highest","height","?","Give","me","the","catalog","entry","name","."]},"325":{"db_id":"product_catalog","query":"SELECT catalog_entry_name FROM catalog_contents ORDER BY capacity ASC LIMIT 1","question":"Find the name of the product that has the smallest capacity.","query_toks":["SELECT","catalog_entry_name","FROM","catalog_contents","ORDER","BY","capacity","ASC","LIMIT","1"],"query_toks_no_value":["select","catalog_entry_name","from","catalog_contents","order","by","capacity","asc","limit","value"],"question_toks":["Find","the","name","of","the","product","that","has","the","smallest","capacity","."]},"326":{"db_id":"product_catalog","query":"SELECT catalog_entry_name FROM catalog_contents ORDER BY capacity ASC LIMIT 1","question":"Which catalog content has the smallest capacity? Return the catalog entry name.","query_toks":["SELECT","catalog_entry_name","FROM","catalog_contents","ORDER","BY","capacity","ASC","LIMIT","1"],"query_toks_no_value":["select","catalog_entry_name","from","catalog_contents","order","by","capacity","asc","limit","value"],"question_toks":["Which","catalog","content","has","the","smallest","capacity","?","Return","the","catalog","entry","name","."]},"327":{"db_id":"product_catalog","query":"SELECT catalog_entry_name FROM catalog_contents WHERE product_stock_number LIKE \"2%\"","question":"Find the names of all the products whose stock number starts with \"2\".","query_toks":["SELECT","catalog_entry_name","FROM","catalog_contents","WHERE","product_stock_number","LIKE","``","2","%","''"],"query_toks_no_value":["select","catalog_entry_name","from","catalog_contents","where","product_stock_number","like","value"],"question_toks":["Find","the","names","of","all","the","products","whose","stock","number","starts","with","``","2","''","."]},"328":{"db_id":"product_catalog","query":"SELECT catalog_entry_name FROM catalog_contents WHERE product_stock_number LIKE \"2%\"","question":"Which catalog contents have a product stock number that starts from \"2\"? Show the catalog entry names.","query_toks":["SELECT","catalog_entry_name","FROM","catalog_contents","WHERE","product_stock_number","LIKE","``","2","%","''"],"query_toks_no_value":["select","catalog_entry_name","from","catalog_contents","where","product_stock_number","like","value"],"question_toks":["Which","catalog","contents","have","a","product","stock","number","that","starts","from","``","2","''","?","Show","the","catalog","entry","names","."]},"329":{"db_id":"product_catalog","query":"SELECT t1.catalog_entry_name FROM Catalog_Contents AS t1 JOIN Catalog_Contents_Additional_Attributes AS t2 ON t1.catalog_entry_id  =  t2.catalog_entry_id WHERE t2.catalog_level_number  =  \"8\"","question":"Find the names of catalog entries with level number 8.","query_toks":["SELECT","t1.catalog_entry_name","FROM","Catalog_Contents","AS","t1","JOIN","Catalog_Contents_Additional_Attributes","AS","t2","ON","t1.catalog_entry_id","=","t2.catalog_entry_id","WHERE","t2.catalog_level_number","=","``","8","''"],"query_toks_no_value":["select","t1",".","catalog_entry_name","from","catalog_contents","as","t1","join","catalog_contents_additional_attributes","as","t2","on","t1",".","catalog_entry_id","=","t2",".","catalog_entry_id","where","t2",".","catalog_level_number","=","value"],"question_toks":["Find","the","names","of","catalog","entries","with","level","number","8","."]},"330":{"db_id":"product_catalog","query":"SELECT t1.catalog_entry_name FROM Catalog_Contents AS t1 JOIN Catalog_Contents_Additional_Attributes AS t2 ON t1.catalog_entry_id  =  t2.catalog_entry_id WHERE t2.catalog_level_number  =  \"8\"","question":"What are the names of catalog entries with level number 8?","query_toks":["SELECT","t1.catalog_entry_name","FROM","Catalog_Contents","AS","t1","JOIN","Catalog_Contents_Additional_Attributes","AS","t2","ON","t1.catalog_entry_id","=","t2.catalog_entry_id","WHERE","t2.catalog_level_number","=","``","8","''"],"query_toks_no_value":["select","t1",".","catalog_entry_name","from","catalog_contents","as","t1","join","catalog_contents_additional_attributes","as","t2","on","t1",".","catalog_entry_id","=","t2",".","catalog_entry_id","where","t2",".","catalog_level_number","=","value"],"question_toks":["What","are","the","names","of","catalog","entries","with","level","number","8","?"]},"331":{"db_id":"product_catalog","query":"SELECT catalog_entry_name FROM catalog_contents WHERE LENGTH  <  3 OR width  >  5","question":"Find the names of the products with length smaller than 3 or height greater than 5.","query_toks":["SELECT","catalog_entry_name","FROM","catalog_contents","WHERE","LENGTH","<","3","OR","width",">","5"],"query_toks_no_value":["select","catalog_entry_name","from","catalog_contents","where","length","<","value","or","width",">","value"],"question_toks":["Find","the","names","of","the","products","with","length","smaller","than","3","or","height","greater","than","5","."]},"332":{"db_id":"product_catalog","query":"SELECT catalog_entry_name FROM catalog_contents WHERE LENGTH  <  3 OR width  >  5","question":"Which catalog contents have length below 3 or above 5? Find the catalog entry names.","query_toks":["SELECT","catalog_entry_name","FROM","catalog_contents","WHERE","LENGTH","<","3","OR","width",">","5"],"query_toks_no_value":["select","catalog_entry_name","from","catalog_contents","where","length","<","value","or","width",">","value"],"question_toks":["Which","catalog","contents","have","length","below","3","or","above","5","?","Find","the","catalog","entry","names","."]},"333":{"db_id":"product_catalog","query":"SELECT t1.attribute_name ,  t1.attribute_id FROM Attribute_Definitions AS t1 JOIN Catalog_Contents_Additional_Attributes AS t2 ON t1.attribute_id  =  t2.attribute_id WHERE t2.attribute_value  =  0","question":"Find the name and attribute ID of the attribute definitions with attribute value 0.","query_toks":["SELECT","t1.attribute_name",",","t1.attribute_id","FROM","Attribute_Definitions","AS","t1","JOIN","Catalog_Contents_Additional_Attributes","AS","t2","ON","t1.attribute_id","=","t2.attribute_id","WHERE","t2.attribute_value","=","0"],"query_toks_no_value":["select","t1",".","attribute_name",",","t1",".","attribute_id","from","attribute_definitions","as","t1","join","catalog_contents_additional_attributes","as","t2","on","t1",".","attribute_id","=","t2",".","attribute_id","where","t2",".","attribute_value","=","value"],"question_toks":["Find","the","name","and","attribute","ID","of","the","attribute","definitions","with","attribute","value","0","."]},"334":{"db_id":"product_catalog","query":"SELECT t1.attribute_name ,  t1.attribute_id FROM Attribute_Definitions AS t1 JOIN Catalog_Contents_Additional_Attributes AS t2 ON t1.attribute_id  =  t2.attribute_id WHERE t2.attribute_value  =  0","question":"Which attribute definitions have attribute value 0? Give me the attribute name and attribute ID.","query_toks":["SELECT","t1.attribute_name",",","t1.attribute_id","FROM","Attribute_Definitions","AS","t1","JOIN","Catalog_Contents_Additional_Attributes","AS","t2","ON","t1.attribute_id","=","t2.attribute_id","WHERE","t2.attribute_value","=","0"],"query_toks_no_value":["select","t1",".","attribute_name",",","t1",".","attribute_id","from","attribute_definitions","as","t1","join","catalog_contents_additional_attributes","as","t2","on","t1",".","attribute_id","=","t2",".","attribute_id","where","t2",".","attribute_value","=","value"],"question_toks":["Which","attribute","definitions","have","attribute","value","0","?","Give","me","the","attribute","name","and","attribute","ID","."]},"335":{"db_id":"product_catalog","query":"SELECT catalog_entry_name ,  capacity FROM Catalog_Contents WHERE price_in_dollars  >  700","question":"Find the name and capacity of products with price greater than 700 (in USD).","query_toks":["SELECT","catalog_entry_name",",","capacity","FROM","Catalog_Contents","WHERE","price_in_dollars",">","700"],"query_toks_no_value":["select","catalog_entry_name",",","capacity","from","catalog_contents","where","price_in_dollars",">","value"],"question_toks":["Find","the","name","and","capacity","of","products","with","price","greater","than","700","(","in","USD",")","."]},"336":{"db_id":"product_catalog","query":"SELECT catalog_entry_name ,  capacity FROM Catalog_Contents WHERE price_in_dollars  >  700","question":"Which catalog contents has price above 700 dollars? Show their catalog entry names and capacities.","query_toks":["SELECT","catalog_entry_name",",","capacity","FROM","Catalog_Contents","WHERE","price_in_dollars",">","700"],"query_toks_no_value":["select","catalog_entry_name",",","capacity","from","catalog_contents","where","price_in_dollars",">","value"],"question_toks":["Which","catalog","contents","has","price","above","700","dollars","?","Show","their","catalog","entry","names","and","capacities","."]},"337":{"db_id":"product_catalog","query":"SELECT date_of_latest_revision FROM Catalogs GROUP BY date_of_latest_revision HAVING count(*)  >  1","question":"Find the dates on which more than one revisions were made.","query_toks":["SELECT","date_of_latest_revision","FROM","Catalogs","GROUP","BY","date_of_latest_revision","HAVING","count","(","*",")",">","1"],"query_toks_no_value":["select","date_of_latest_revision","from","catalogs","group","by","date_of_latest_revision","having","count","(","*",")",">","value"],"question_toks":["Find","the","dates","on","which","more","than","one","revisions","were","made","."]},"338":{"db_id":"product_catalog","query":"SELECT date_of_latest_revision FROM Catalogs GROUP BY date_of_latest_revision HAVING count(*)  >  1","question":"On which days more than one revisions were made on catalogs.","query_toks":["SELECT","date_of_latest_revision","FROM","Catalogs","GROUP","BY","date_of_latest_revision","HAVING","count","(","*",")",">","1"],"query_toks_no_value":["select","date_of_latest_revision","from","catalogs","group","by","date_of_latest_revision","having","count","(","*",")",">","value"],"question_toks":["On","which","days","more","than","one","revisions","were","made","on","catalogs","."]},"339":{"db_id":"product_catalog","query":"SELECT count(*) FROM catalog_contents","question":"How many products are there in the records?","query_toks":["SELECT","count","(","*",")","FROM","catalog_contents"],"query_toks_no_value":["select","count","(","*",")","from","catalog_contents"],"question_toks":["How","many","products","are","there","in","the","records","?"]},"340":{"db_id":"product_catalog","query":"SELECT count(*) FROM catalog_contents","question":"Find the total number of catalog contents.","query_toks":["SELECT","count","(","*",")","FROM","catalog_contents"],"query_toks_no_value":["select","count","(","*",")","from","catalog_contents"],"question_toks":["Find","the","total","number","of","catalog","contents","."]},"341":{"db_id":"product_catalog","query":"SELECT catalog_entry_name FROM catalog_contents WHERE next_entry_id  >  8","question":"Name all the products with next entry ID greater than 8.","query_toks":["SELECT","catalog_entry_name","FROM","catalog_contents","WHERE","next_entry_id",">","8"],"query_toks_no_value":["select","catalog_entry_name","from","catalog_contents","where","next_entry_id",">","value"],"question_toks":["Name","all","the","products","with","next","entry","ID","greater","than","8","."]},"342":{"db_id":"product_catalog","query":"SELECT catalog_entry_name FROM catalog_contents WHERE next_entry_id  >  8","question":"What are the catalog entry names of the products with next entry ID above 8?","query_toks":["SELECT","catalog_entry_name","FROM","catalog_contents","WHERE","next_entry_id",">","8"],"query_toks_no_value":["select","catalog_entry_name","from","catalog_contents","where","next_entry_id",">","value"],"question_toks":["What","are","the","catalog","entry","names","of","the","products","with","next","entry","ID","above","8","?"]}}